torchmocks/__init__.py
torchmocks/torchmocks.py
torchmocks/nn/activation.py
torchmocks/nn/conv.py
torchmocks/nn/dropout.py
torchmocks/nn/embedding.py
torchmocks/nn/linear.py
torchmocks/nn/normalization.py
torchmocks/nn/pooling.py
torchmocks-0.1.0.dist-info/METADATA
torchmocks-0.1.0.dist-info/WHEEL
torchmocks-0.1.0.dist-info/licenses/LICENSE
torchmocks-0.1.0.dist-info/RECORD
