Metadata-Version: 2.1
Name: torchmocks
Version: 0.1.0
Summary: Mocks pytorch modules so that test run faster
Project-URL: Homepage, https://github.com/nathanbreitsch/torchmocks
Author: Nathan Breitsch
License: MIT
License-File: LICENSE
Keywords: deep learning,machine learning,neural networks,scientific computations,torchmocks
Classifier: Intended Audience :: Science/Research
Classifier: License :: OSI Approved :: MIT License
Classifier: Programming Language :: Python :: 3
Requires-Python: >=3.7
Requires-Dist: torch
